omni/__init__.py
omni/pro/__init__.py
omni/pro/check_migration.py
omni/pro/cloudmap.py
omni/pro/config.py
omni/pro/database_connection.py
omni/pro/decorators.py
omni/pro/descriptor.py
omni/pro/exceptions.py
omni/pro/files.py
omni/pro/grpc_interceptor.py
omni/pro/import_export.py
omni/pro/initial.py
omni/pro/locales.py
omni/pro/logger.py
omni/pro/microservice.py
omni/pro/redis.py
omni/pro/register.py
omni/pro/stack.py
omni/pro/topology.py
omni/pro/util.py
omni/pro/validators.py
omni/pro/aws/__init__.py
omni/pro/aws/client.py
omni/pro/aws/cloudmap.py
omni/pro/aws/cognito.py
omni/pro/aws/s3.py
omni/pro/data/models.user.csv
omni/pro/database/__init__.py
omni/pro/database/mongo.py
omni/pro/database/postgres.py
omni/pro/database/redis.py
omni/pro/database/sqlalchemy.py
omni/pro/models/__init__.py
omni/pro/models/base.py
omni/pro/models/logger.py
omni/pro/protos/__init__.py
omni/pro/protos/grpc_connector.py
omni/pro/protos/grpc_function.py
omni/pro/protos/response.py
omni/pro/protos/util.py
omni/pro/protos/common/__init__.py
omni/pro/protos/common/base_pb2.py
omni/pro/protos/common/base_pb2.pyi
omni/pro/protos/common/base_pb2_grpc.py
omni/pro/protos/v1/__init__.py
omni/pro/protos/v1/catalogs/__init__.py
omni/pro/protos/v1/catalogs/family_pb2.py
omni/pro/protos/v1/catalogs/family_pb2.pyi
omni/pro/protos/v1/catalogs/family_pb2_grpc.py
omni/pro/protos/v1/catalogs/template_pb2.py
omni/pro/protos/v1/catalogs/template_pb2.pyi
omni/pro/protos/v1/catalogs/template_pb2_grpc.py
omni/pro/protos/v1/clients/__init__.py
omni/pro/protos/v1/clients/address_pb2.py
omni/pro/protos/v1/clients/address_pb2.pyi
omni/pro/protos/v1/clients/address_pb2_grpc.py
omni/pro/protos/v1/clients/client_pb2.py
omni/pro/protos/v1/clients/client_pb2.pyi
omni/pro/protos/v1/clients/client_pb2_grpc.py
omni/pro/protos/v1/clients/type_document_pb2.py
omni/pro/protos/v1/clients/type_document_pb2.pyi
omni/pro/protos/v1/clients/type_document_pb2_grpc.py
omni/pro/protos/v1/rules/__init__.py
omni_pro-0.1.228.dist-info/LICENSE
omni_pro-0.1.228.dist-info/METADATA
omni_pro-0.1.228.dist-info/WHEEL
omni_pro-0.1.228.dist-info/top_level.txt
omni_pro-0.1.228.dist-info/RECORD
