Metadata-Version: 2.1
Name: omni-pro
Version: 0.1.228
Summary: Python library designed to be a utility for OMS microservices
Home-page: https://github.com/Omnipro-Solutions/saas-ms-library
Author: OMNI.PRO
Author-email: development@omni.pro
License: MIT
Classifier: Development Status :: 3 - Alpha
Classifier: Intended Audience :: Developers
Classifier: License :: OSI Approved :: MIT License
Classifier: Programming Language :: Python :: 3.9
Requires-Python: >=3.9
License-File: LICENSE
Requires-Dist: protobuf ==4.23.4
Requires-Dist: grpcio ==1.56.0
Requires-Dist: grpcio-tools ==1.56.0
Requires-Dist: boto3 ==1.28.4
Requires-Dist: mongoengine ==0.27.0
Requires-Dist: marshmallow ==3.19.0
Requires-Dist: hiredis ==2.2.3
Requires-Dist: redis ==4.6.0
Requires-Dist: fakeredis[json] ==2.17.0
Requires-Dist: SQLAlchemy ==2.0.19
Requires-Dist: networkx ==3.1
Requires-Dist: unidecode ==1.3.8
Provides-Extra: dev
Requires-Dist: pytest ; extra == 'dev'
